pytest_xdist_gnumake/__init__.py
pytest_xdist_gnumake/jobserver_client.py
pytest_xdist_gnumake/plugin.py
pytest_xdist_gnumake-1.0.0.dist-info/licenses/LICENSE
pytest_xdist_gnumake-1.0.0.dist-info/METADATA
pytest_xdist_gnumake-1.0.0.dist-info/WHEEL
pytest_xdist_gnumake-1.0.0.dist-info/entry_points.txt
pytest_xdist_gnumake-1.0.0.dist-info/top_level.txt
pytest_xdist_gnumake-1.0.0.dist-info/RECORD
