Metadata-Version: 2.4
Name: pytest-xdist-gnumake
Version: 1.0.0
Summary: A small example package
Author-email: Volker Braun <vbraun.name@gmail.com>
License-Expression: Apache-2.0
Project-URL: Homepage, https://github.com/vbraun/pytest-xdist-gnumake
Classifier: Programming Language :: Python :: 3
Classifier: Operating System :: OS Independent
Requires-Python: >=3.11
License-File: LICENSE
Requires-Dist: pytest
Requires-Dist: pytest-xdist
Requires-Dist: gnumake-tokenpool
Provides-Extra: dev
Requires-Dist: mypy; extra == "dev"
Requires-Dist: filelock; extra == "dev"
Dynamic: license-file
